telebot_router/__init__.py
balebotii-1.0.0.dist-info/LICENSE
balebotii-1.0.0.dist-info/METADATA
balebotii-1.0.0.dist-info/WHEEL
balebotii-1.0.0.dist-info/top_level.txt
balebotii-1.0.0.dist-info/RECORD
