Metadata-Version: 2.1
Name: balebotii
Version: 1.0.0
Summary: Bale api bot
Author-email: taharahmani <tahazoha77@gmail.com>
Classifier: Programming Language :: Python :: 3
Classifier: License :: OSI Approved :: MIT License
Classifier: Operating System :: OS Independent
Requires-Python: >=3.8
License-File: LICENSE
